atikin_utils/__init__.py
atikin_utils/async_utils.py
atikin_utils/cli.py
atikin_utils/config.py
atikin_utils/decorators.py
atikin_utils/dt.py
atikin_utils/env.py
atikin_utils/files.py
atikin_utils/logging_utils.py
atikin_utils/network.py
atikin_utils/paths.py
atikin_utils/security.py
atikin_utils/strings.py
atikin_utils-0.1.0.dist-info/licenses/LICENSE
atikin_utils-0.1.0.dist-info/METADATA
atikin_utils-0.1.0.dist-info/WHEEL
atikin_utils-0.1.0.dist-info/top_level.txt
atikin_utils-0.1.0.dist-info/RECORD
