Metadata-Version: 2.4
Name: atikin-utils
Version: 0.1.0
Summary: Small collection of daily utilities for developers: string helpers, friendly datetime utils, file helpers (auto backup/create) and a tiny env manager. created by Atikin Verse.
Author-email: Atikin Verse <atikinverse@gmail.com>
License: MIT
Keywords: utilities,devtools,datetime,date,time,timestamp,humanize,formatting,env,environment,dotenv,config,settings,configuration,variables,file,files,filesystem,backup,auto-backup,file-helpers,file-io,strings,string-utils,text,text-processing,case-conversion,slugify,helper,helpers,shortcuts,toolkit,utils,utility-functions,developer-tools,python-utilities,productivity,automation,scripting,cli,python-tools,everyday-tools,handy-utils,data,data-utils,data-tools,file-management,lightweight,atikin,a
Classifier: Programming Language :: Python :: 3
Classifier: License :: OSI Approved :: MIT License
Classifier: Operating System :: OS Independent
Requires-Python: >=3.9
License-File: LICENSE
Dynamic: license-file
